k3zkutil/__init__.py
k3zkutil/cached_reader.py
k3zkutil/exceptions.py
k3zkutil/synopsis.py
k3zkutil/zkacid.py
k3zkutil/zkconf.py
k3zkutil/zklock.py
k3zkutil/zkutil.py
k3zkutil-0.1.6.dist-info/licenses/LICENSE
k3zkutil-0.1.6.dist-info/METADATA
k3zkutil-0.1.6.dist-info/WHEEL
k3zkutil-0.1.6.dist-info/top_level.txt
k3zkutil-0.1.6.dist-info/RECORD
